Metadata-Version: 2.1
Name: jason-test
Version: 1.0.0
Summary: jason_test
Author: jason
License: UNKNOWN
Platform: UNKNOWN
